content_counter/__init__.py
content_counter/counter.py
counter/__init__.py
counter/contentcounter.py
peretz_counter-0.1.2.dist-info/METADATA
peretz_counter-0.1.2.dist-info/WHEEL
peretz_counter-0.1.2.dist-info/top_level.txt
peretz_counter-0.1.2.dist-info/RECORD
