Metadata-Version: 2.1
Name: peretz-counter
Version: 0.1.2
Summary: P2 - content counter.
Home-page: https://github.com/me/myproject
Author: Peretz Rickett
Author-email: peretz@rickett.us
License: MIT
Platform: UNKNOWN
Classifier: License :: OSI Approved :: MIT License
Classifier: Programming Language :: Python
Classifier: Programming Language :: Python :: 3
Classifier: Programming Language :: Python :: 3.8
Classifier: Programming Language :: Python :: Implementation :: CPython
Classifier: Programming Language :: Python :: Implementation :: PyPy
Requires-Python: >=3.8.0
Requires-Dist: peretz-fetcher
Requires-Dist: boto3
